stateops/__init__.py
state_op-0.0.1.dist-info/METADATA
state_op-0.0.1.dist-info/WHEEL
state_op-0.0.1.dist-info/top_level.txt
state_op-0.0.1.dist-info/RECORD
