Metadata-Version: 2.1
Name: state-op
Version: 0.0.1
Summary: A state engine for natural language processing that supports custom operators
Home-page: https://github.com/DengBoCong/state-op
Author: DengBoCong
Author-email: bocongdeng@gmail.com
License: MIT License
Project-URL: Bug Reports, https://github.com/DengBoCong/state-op/issues
Project-URL: Funding, https://github.com/DengBoCong/state-op
Project-URL: Source, https://github.com/DengBoCong/state-op
Keywords: state,nlp
Platform: UNKNOWN
Classifier: Programming Language :: Python :: 3
Classifier: Programming Language :: Python :: 3.6
Classifier: Programming Language :: Python :: 3.7
Classifier: Programming Language :: Python :: 3.8
Classifier: License :: OSI Approved :: MIT License
Classifier: Operating System :: OS Independent
